isupdated.py
isupdated-0.1.1.dist-info/METADATA
isupdated-0.1.1.dist-info/WHEEL
isupdated-0.1.1.dist-info/license.txt
isupdated-0.1.1.dist-info/top_level.txt
isupdated-0.1.1.dist-info/RECORD
